{
  ":BattleMapGroup": {
    ":type": {
      "id": "key",
      "name": "string",
      "battleMap": [
        {
          "id": "number",
          "rate": "number"
        },
        {
          "id": "number",
          "rate": "number"
        },
        {
          "id": "number",
          "rate": "number"
        },
        {
          "id": "number",
          "rate": "number"
        },
        {
          "id": "number",
          "rate": "number"
        },
        {
          "id": "number",
          "rate": "number"
        },
        {
          "id": "number",
          "rate": "number"
        },
        {
          "id": "number",
          "rate": "number"
        },
        {
          "id": "number",
          "rate": "number"
        },
        {
          "id": "number",
          "rate": "number"
        },
        {
          "id": "number",
          "rate": "number"
        }
      ],
      "needLv": "number",
      "battleMapLowLv": [
        {
          "id": "number",
          "rate": "number"
        },
        {
          "id": "number",
          "rate": "number"
        },
        {
          "id": "number",
          "rate": "number"
        },
        {
          "id": "number",
          "rate": "number"
        },
        {
          "id": "number",
          "rate": "number"
        }
      ]
    },
    ":required": {
      "name": 1,
      "battleMap": [
        {
          "id": 1,
          "rate": 1
        }
      ]
    },
    ":requiredInObject": {
      "battleMap": [
        {
          "id": 1,
          "rate": 1
        }
      ]
    },
    ":min": {
      "battleMap": [
        {
          "id": 64300000
        },
        {
          "id": 64300000
        },
        {
          "id": 64300000
        },
        {
          "id": 64300000
        },
        {
          "id": 64300000
        },
        {
          "id": 64300000
        },
        {
          "id": 64300000
        },
        {
          "id": 64300000
        },
        {
          "id": 64300000
        },
        {
          "id": 64300000
        },
        {
          "id": 64300000
        }
      ],
      "battleMapLowLv": [
        {
          "id": 64300000
        },
        {
          "id": 64300000
        },
        {
          "id": 64300000
        },
        {
          "id": 64300000
        },
        {
          "id": 64300000
        }
      ]
    },
    ":max": {
      "battleMap": [
        {
          "id": 64499999
        },
        {
          "id": 64499999
        },
        {
          "id": 64499999
        },
        {
          "id": 64499999
        },
        {
          "id": 64499999
        },
        {
          "id": 64499999
        },
        {
          "id": 64499999
        },
        {
          "id": 64499999
        },
        {
          "id": 64499999
        },
        {
          "id": 64499999
        },
        {
          "id": 64499999
        }
      ],
      "battleMapLowLv": [
        {
          "id": 64499999
        },
        {
          "id": 64499999
        },
        {
          "id": 64499999
        },
        {
          "id": 64499999
        },
        {
          "id": 64499999
        }
      ]
    },
    ":enum": {},
    ":links": {
      "battleMap": [
        {
          "id": ["BattleMap"]
        },
        {
          "id": ["BattleMap"]
        },
        {
          "id": ["BattleMap"]
        },
        {
          "id": ["BattleMap"]
        },
        {
          "id": ["BattleMap"]
        },
        {
          "id": ["BattleMap"]
        },
        {
          "id": ["BattleMap"]
        },
        {
          "id": ["BattleMap"]
        },
        {
          "id": ["BattleMap"]
        },
        {
          "id": ["BattleMap"]
        },
        {
          "id": ["BattleMap"]
        }
      ],
      "battleMapLowLv": [
        {
          "id": ["BattleMap"]
        },
        {
          "id": ["BattleMap"]
        },
        {
          "id": ["BattleMap"]
        },
        {
          "id": ["BattleMap"]
        },
        {
          "id": ["BattleMap"]
        }
      ]
    }
  },
  "BattleMapGroup": {
    "64500000": {
      "id": 64500000,
      "name": "해안_초원 지형",
      "battleMap": [
        {
          "id": 64310001,
          "rate": 20
        },
        {
          "id": 64310002,
          "rate": 40
        },
        {
          "id": 64310003,
          "rate": 40
        },
        {
          "id": 64310004,
          "rate": 20
        },
        {
          "id": 64310005,
          "rate": 20
        },
        {
          "id": 64310006,
          "rate": 40
        },
        {
          "id": 64310007,
          "rate": 20
        },
        {
          "id": 64310008,
          "rate": 40
        }
      ],
      "needLv": 10,
      "battleMapLowLv": [
        {
          "id": 64310001,
          "rate": 40
        },
        {
          "id": 64310003,
          "rate": 40
        },
        {
          "id": 64310005,
          "rate": 40
        }
      ]
    },
    "64500001": {
      "id": 64500001,
      "name": "해안_사막 지형",
      "battleMap": [
        {
          "id": 64310009,
          "rate": 40
        },
        {
          "id": 64310010,
          "rate": 15
        },
        {
          "id": 64310011,
          "rate": 20
        },
        {
          "id": 64310012,
          "rate": 40
        }
      ],
      "needLv": 10,
      "battleMapLowLv": [
        {
          "id": 64310010,
          "rate": 40
        },
        {
          "id": 64310011,
          "rate": 40
        }
      ]
    },
    "64500002": {
      "id": 64500002,
      "name": "해안_눈 지형",
      "battleMap": [
        {
          "id": 64310013,
          "rate": 20
        },
        {
          "id": 64310014,
          "rate": 40
        },
        {
          "id": 64310015,
          "rate": 15
        },
        {
          "id": 64310016,
          "rate": 40
        }
      ],
      "needLv": 10,
      "battleMapLowLv": [
        {
          "id": 64310015,
          "rate": 40
        }
      ]
    },
    "64500003": {
      "id": 64500003,
      "name": "만_초원 지형",
      "battleMap": [
        {
          "id": 64310101,
          "rate": 20
        },
        {
          "id": 64310102,
          "rate": 20
        },
        {
          "id": 64310103,
          "rate": 15
        },
        {
          "id": 64310104,
          "rate": 20
        },
        {
          "id": 64310109,
          "rate": 15
        }
      ],
      "needLv": 10,
      "battleMapLowLv": [
        {
          "id": 64310102,
          "rate": 40
        },
        {
          "id": 64310103,
          "rate": 40
        }
      ]
    },
    "64500004": {
      "id": 64500004,
      "name": "만_사막 지형",
      "battleMap": [
        {
          "id": 64310105,
          "rate": 20
        },
        {
          "id": 64310106,
          "rate": 20
        }
      ],
      "needLv": 10,
      "battleMapLowLv": [
        {
          "id": 64310105,
          "rate": 40
        },
        {
          "id": 64310106,
          "rate": 40
        }
      ]
    },
    "64500005": {
      "id": 64500005,
      "name": "만_눈 지형",
      "battleMap": [
        {
          "id": 64310107,
          "rate": 40
        },
        {
          "id": 64310108,
          "rate": 20
        }
      ],
      "needLv": 10,
      "battleMapLowLv": [
        {
          "id": 64310108,
          "rate": 40
        }
      ]
    },
    "64500006": {
      "id": 64500006,
      "name": "곶_초원 지형",
      "battleMap": [
        {
          "id": 64310201,
          "rate": 20
        },
        {
          "id": 64310102,
          "rate": 15
        },
        {
          "id": 64310204,
          "rate": 20
        },
        {
          "id": 64310103,
          "rate": 15
        }
      ],
      "needLv": 10,
      "battleMapLowLv": [
        {
          "id": 64310201,
          "rate": 40
        }
      ]
    },
    "64500007": {
      "id": 64500007,
      "name": "곶_사막 지형",
      "battleMap": [
        {
          "id": 64310105,
          "rate": 20
        },
        {
          "id": 64310206,
          "rate": 20
        }
      ],
      "needLv": 10,
      "battleMapLowLv": [
        {
          "id": 64310204,
          "rate": 40
        }
      ]
    },
    "64500008": {
      "id": 64500008,
      "name": "곶_눈 지형",
      "battleMap": [
        {
          "id": 64310207,
          "rate": 40
        },
        {
          "id": 64310208,
          "rate": 40
        }
      ],
      "needLv": 10,
      "battleMapLowLv": [
        {
          "id": 64310207,
          "rate": 40
        }
      ]
    },
    "64500009": {
      "id": 64500009,
      "name": "유빙_초원 지형",
      "battleMap": [
        {
          "id": 64310301,
          "rate": 20
        },
        {
          "id": 64310302,
          "rate": 20
        },
        {
          "id": 64310303,
          "rate": 20
        },
        {
          "id": 64310304,
          "rate": 20
        }
      ],
      "needLv": 10,
      "battleMapLowLv": [
        {
          "id": 64310301,
          "rate": 40
        }
      ]
    },
    "64500010": {
      "id": 64500010,
      "name": "유빙_사막 지형",
      "battleMap": [
        {
          "id": 64310305,
          "rate": 20
        },
        {
          "id": 64310306,
          "rate": 20
        }
      ],
      "needLv": 10,
      "battleMapLowLv": [
        {
          "id": 64310306,
          "rate": 40
        }
      ]
    },
    "64500011": {
      "id": 64500011,
      "name": "유빙_눈 지형",
      "battleMap": [
        {
          "id": 64310307,
          "rate": 20
        },
        {
          "id": 64310308,
          "rate": 40
        }
      ],
      "needLv": 10,
      "battleMapLowLv": [
        {
          "id": 64310307,
          "rate": 40
        }
      ]
    },
    "64500012": {
      "id": 64500012,
      "name": "다도_초원 지형",
      "battleMap": [
        {
          "id": 64310401,
          "rate": 20
        },
        {
          "id": 64310402,
          "rate": 20
        },
        {
          "id": 64310403,
          "rate": 20
        },
        {
          "id": 64310404,
          "rate": 20
        },
        {
          "id": 64310409,
          "rate": 15
        },
        {
          "id": 64310410,
          "rate": 20
        },
        {
          "id": 64310411,
          "rate": 20
        }
      ],
      "needLv": 10,
      "battleMapLowLv": [
        {
          "id": 64310402,
          "rate": 40
        },
        {
          "id": 64310404,
          "rate": 40
        },
        {
          "id": 64310410,
          "rate": 40
        },
        {
          "id": 64310411,
          "rate": 40
        }
      ]
    },
    "64500013": {
      "id": 64500013,
      "name": "다도_사막 지형",
      "battleMap": [
        {
          "id": 64310405,
          "rate": 20
        },
        {
          "id": 64310406,
          "rate": 20
        },
        {
          "id": 64310413,
          "rate": 20
        },
        {
          "id": 64310414,
          "rate": 20
        }
      ],
      "needLv": 10,
      "battleMapLowLv": [
        {
          "id": 64310406,
          "rate": 40
        }
      ]
    },
    "64500014": {
      "id": 64500014,
      "name": "다도_눈 지형",
      "battleMap": [
        {
          "id": 64310408,
          "rate": 20
        },
        {
          "id": 64310417,
          "rate": 40
        },
        {
          "id": 64310418,
          "rate": 20
        }
      ],
      "needLv": 10,
      "battleMapLowLv": [
        {
          "id": 64310408,
          "rate": 40
        }
      ]
    },
    "64500015": {
      "id": 64500015,
      "name": "대형섬_초원 지형",
      "battleMap": [
        {
          "id": 64310501,
          "rate": 15
        },
        {
          "id": 64310502,
          "rate": 20
        },
        {
          "id": 64310504,
          "rate": 20
        },
        {
          "id": 64310509,
          "rate": 20
        },
        {
          "id": 64310510,
          "rate": 15
        }
      ],
      "needLv": 10,
      "battleMapLowLv": [
        {
          "id": 64310501,
          "rate": 40
        },
        {
          "id": 64310504,
          "rate": 40
        },
        {
          "id": 64310509,
          "rate": 40
        }
      ]
    },
    "64500016": {
      "id": 64500016,
      "name": "대형섬_사막 지형",
      "battleMap": [
        {
          "id": 64310505,
          "rate": 20
        },
        {
          "id": 64310506,
          "rate": 40
        }
      ],
      "needLv": 10,
      "battleMapLowLv": [
        {
          "id": 64310506,
          "rate": 40
        }
      ]
    },
    "64500017": {
      "id": 64500017,
      "name": "대형섬_눈 지형",
      "battleMap": [
        {
          "id": 64310507,
          "rate": 20
        },
        {
          "id": 64310508,
          "rate": 20
        }
      ],
      "needLv": 10,
      "battleMapLowLv": [
        {
          "id": 64310508,
          "rate": 40
        }
      ]
    },
    "64500018": {
      "id": 64500018,
      "name": "일반강_초원 지형",
      "battleMap": [
        {
          "id": 64310601,
          "rate": 20
        },
        {
          "id": 64310603,
          "rate": 15
        },
        {
          "id": 64310604,
          "rate": 10
        }
      ],
      "needLv": 10,
      "battleMapLowLv": [
        {
          "id": 64310601,
          "rate": 40
        }
      ]
    },
    "64500019": {
      "id": 64500019,
      "name": "일반강_사막 지형",
      "battleMap": [
        {
          "id": 64310605,
          "rate": 20
        },
        {
          "id": 64310606,
          "rate": 20
        }
      ],
      "needLv": 10,
      "battleMapLowLv": [
        {
          "id": 64310605,
          "rate": 40
        }
      ]
    },
    "64500020": {
      "id": 64500020,
      "name": "일반강_눈 지형",
      "battleMap": [
        {
          "id": 64310607,
          "rate": 20
        },
        {
          "id": 64310608,
          "rate": 20
        }
      ],
      "needLv": 10,
      "battleMapLowLv": [
        {
          "id": 64310607,
          "rate": 40
        }
      ]
    },
    "64500021": {
      "id": 64500021,
      "name": "구불거리는강_초원 지형",
      "battleMap": [
        {
          "id": 64310701,
          "rate": 20
        },
        {
          "id": 64310702,
          "rate": 20
        },
        {
          "id": 64310703,
          "rate": 15
        },
        {
          "id": 64310704,
          "rate": 15
        }
      ],
      "needLv": 10,
      "battleMapLowLv": [
        {
          "id": 64310701,
          "rate": 40
        }
      ]
    },
    "64500022": {
      "id": 64500022,
      "name": "구불거리는강_사막 지형",
      "battleMap": [
        {
          "id": 64310705,
          "rate": 20
        },
        {
          "id": 64310706,
          "rate": 15
        }
      ],
      "needLv": 10,
      "battleMapLowLv": [
        {
          "id": 64310705,
          "rate": 40
        }
      ]
    },
    "64500023": {
      "id": 64500023,
      "name": "구불거리는강_눈 지형",
      "battleMap": [
        {
          "id": 64310707,
          "rate": 15
        },
        {
          "id": 64310708,
          "rate": 15
        }
      ],
      "needLv": 10,
      "battleMapLowLv": [
        {
          "id": 64310707,
          "rate": 40
        }
      ]
    },
    "64500024": {
      "id": 64500024,
      "name": "모이는강_초원 지형",
      "battleMap": [
        {
          "id": 64310801,
          "rate": 20
        },
        {
          "id": 64310802,
          "rate": 20
        },
        {
          "id": 64310803,
          "rate": 20
        },
        {
          "id": 64310804,
          "rate": 20
        }
      ],
      "needLv": 10,
      "battleMapLowLv": [
        {
          "id": 64310801,
          "rate": 40
        }
      ]
    },
    "64500025": {
      "id": 64500025,
      "name": "모이는강_사막 지형",
      "battleMap": [
        {
          "id": 64310805,
          "rate": 15
        },
        {
          "id": 64310806,
          "rate": 20
        }
      ],
      "needLv": 10,
      "battleMapLowLv": [
        {
          "id": 64310805,
          "rate": 40
        }
      ]
    },
    "64500026": {
      "id": 64500026,
      "name": "모이는강_눈 지형",
      "battleMap": [
        {
          "id": 64310807,
          "rate": 20
        },
        {
          "id": 64310808,
          "rate": 20
        }
      ],
      "needLv": 10,
      "battleMapLowLv": [
        {
          "id": 64310807,
          "rate": 40
        }
      ]
    },
    "64500027": {
      "id": 64500027,
      "name": "해협_초원 지형",
      "battleMap": [
        {
          "id": 64310901,
          "rate": 20
        },
        {
          "id": 64310903,
          "rate": 20
        },
        {
          "id": 64310904,
          "rate": 20
        }
      ],
      "needLv": 10,
      "battleMapLowLv": [
        {
          "id": 64310901,
          "rate": 40
        },
        {
          "id": 64310904,
          "rate": 40
        }
      ]
    },
    "64500028": {
      "id": 64500028,
      "name": "해협_사막 지형",
      "battleMap": [
        {
          "id": 64310905,
          "rate": 20
        },
        {
          "id": 64310906,
          "rate": 20
        }
      ],
      "needLv": 10,
      "battleMapLowLv": [
        {
          "id": 64310905,
          "rate": 40
        }
      ]
    },
    "64500029": {
      "id": 64500029,
      "name": "해협_눈 지형",
      "battleMap": [
        {
          "id": 64310907,
          "rate": 20
        },
        {
          "id": 64310908,
          "rate": 20
        }
      ],
      "needLv": 10,
      "battleMapLowLv": [
        {
          "id": 64310907,
          "rate": 40
        }
      ]
    },
    "64500030": {
      "id": 64500030,
      "name": "육지",
      "battleMap": [
        {
          "id": 64310001,
          "rate": 40
        }
      ]
    },
    "64500031": {
      "id": 64500031,
      "name": "영상촬영용",
      "battleMap": [
        {
          "id": 64310401,
          "rate": 40
        }
      ]
    },
    "64500032": {
      "id": 64500032,
      "name": "좌우반전_해안_초원 지형",
      "battleMap": [
        {
          "id": 64311001,
          "rate": 20
        },
        {
          "id": 64311002,
          "rate": 40
        },
        {
          "id": 64311003,
          "rate": 40
        },
        {
          "id": 64311004,
          "rate": 20
        },
        {
          "id": 64311005,
          "rate": 20
        },
        {
          "id": 64311006,
          "rate": 40
        },
        {
          "id": 64311007,
          "rate": 20
        },
        {
          "id": 64311008,
          "rate": 40
        }
      ],
      "needLv": 10,
      "battleMapLowLv": [
        {
          "id": 64311001,
          "rate": 40
        },
        {
          "id": 64311003,
          "rate": 40
        },
        {
          "id": 64311005,
          "rate": 40
        }
      ]
    },
    "64500033": {
      "id": 64500033,
      "name": "좌우반전_해안_사막 지형",
      "battleMap": [
        {
          "id": 64311009,
          "rate": 40
        },
        {
          "id": 64311010,
          "rate": 15
        },
        {
          "id": 64311011,
          "rate": 20
        },
        {
          "id": 64311012,
          "rate": 40
        }
      ],
      "needLv": 10,
      "battleMapLowLv": [
        {
          "id": 64311010,
          "rate": 40
        },
        {
          "id": 64311011,
          "rate": 40
        }
      ]
    },
    "64500034": {
      "id": 64500034,
      "name": "좌우반전_해안_눈 지형",
      "battleMap": [
        {
          "id": 64311013,
          "rate": 20
        },
        {
          "id": 64311014,
          "rate": 40
        },
        {
          "id": 64311015,
          "rate": 15
        },
        {
          "id": 64311016,
          "rate": 40
        }
      ],
      "needLv": 10,
      "battleMapLowLv": [
        {
          "id": 64311015,
          "rate": 40
        }
      ]
    },
    "64500035": {
      "id": 64500035,
      "name": "좌우반전_만_초원 지형",
      "battleMap": [
        {
          "id": 64311101,
          "rate": 20
        },
        {
          "id": 64311102,
          "rate": 20
        },
        {
          "id": 64311103,
          "rate": 15
        },
        {
          "id": 64311104,
          "rate": 20
        },
        {
          "id": 64311109,
          "rate": 15
        }
      ],
      "needLv": 10,
      "battleMapLowLv": [
        {
          "id": 64311102,
          "rate": 40
        },
        {
          "id": 64311103,
          "rate": 40
        }
      ]
    },
    "64500036": {
      "id": 64500036,
      "name": "좌우반전_만_사막 지형",
      "battleMap": [
        {
          "id": 64311105,
          "rate": 20
        },
        {
          "id": 64311106,
          "rate": 20
        }
      ],
      "needLv": 10,
      "battleMapLowLv": [
        {
          "id": 64311105,
          "rate": 40
        },
        {
          "id": 64311106,
          "rate": 40
        }
      ]
    },
    "64500037": {
      "id": 64500037,
      "name": "좌우반전_만_눈 지형",
      "battleMap": [
        {
          "id": 64311107,
          "rate": 40
        },
        {
          "id": 64311108,
          "rate": 20
        }
      ],
      "needLv": 10,
      "battleMapLowLv": [
        {
          "id": 64311108,
          "rate": 40
        }
      ]
    },
    "64500038": {
      "id": 64500038,
      "name": "좌우반전_곶_초원 지형",
      "battleMap": [
        {
          "id": 64311201,
          "rate": 20
        },
        {
          "id": 64311102,
          "rate": 15
        },
        {
          "id": 64311204,
          "rate": 20
        },
        {
          "id": 64311103,
          "rate": 15
        }
      ],
      "needLv": 10,
      "battleMapLowLv": [
        {
          "id": 64311201,
          "rate": 40
        }
      ]
    },
    "64500039": {
      "id": 64500039,
      "name": "좌우반전_곶_사막 지형",
      "battleMap": [
        {
          "id": 64311105,
          "rate": 20
        },
        {
          "id": 64311206,
          "rate": 20
        }
      ],
      "needLv": 10,
      "battleMapLowLv": [
        {
          "id": 64311204,
          "rate": 40
        }
      ]
    },
    "64500040": {
      "id": 64500040,
      "name": "좌우반전_곶_눈 지형",
      "battleMap": [
        {
          "id": 64311207,
          "rate": 40
        },
        {
          "id": 64311208,
          "rate": 40
        }
      ],
      "needLv": 10,
      "battleMapLowLv": [
        {
          "id": 64311207,
          "rate": 40
        }
      ]
    },
    "64500041": {
      "id": 64500041,
      "name": "좌우반전_유빙_초원 지형",
      "battleMap": [
        {
          "id": 64311301,
          "rate": 20
        },
        {
          "id": 64311302,
          "rate": 20
        },
        {
          "id": 64311303,
          "rate": 20
        },
        {
          "id": 64311304,
          "rate": 20
        }
      ],
      "needLv": 10,
      "battleMapLowLv": [
        {
          "id": 64311301,
          "rate": 40
        }
      ]
    },
    "64500042": {
      "id": 64500042,
      "name": "좌우반전_유빙_사막 지형",
      "battleMap": [
        {
          "id": 64311305,
          "rate": 20
        },
        {
          "id": 64311306,
          "rate": 20
        }
      ],
      "needLv": 10,
      "battleMapLowLv": [
        {
          "id": 64311306,
          "rate": 40
        }
      ]
    },
    "64500043": {
      "id": 64500043,
      "name": "좌우반전_유빙_눈 지형",
      "battleMap": [
        {
          "id": 64311307,
          "rate": 20
        },
        {
          "id": 64311308,
          "rate": 40
        }
      ],
      "needLv": 10,
      "battleMapLowLv": [
        {
          "id": 64311307,
          "rate": 40
        }
      ]
    },
    "64500044": {
      "id": 64500044,
      "name": "좌우반전_다도_초원 지형",
      "battleMap": [
        {
          "id": 64311401,
          "rate": 20
        },
        {
          "id": 64311402,
          "rate": 20
        },
        {
          "id": 64311403,
          "rate": 20
        },
        {
          "id": 64311404,
          "rate": 20
        },
        {
          "id": 64311409,
          "rate": 15
        },
        {
          "id": 64310410,
          "rate": 20
        },
        {
          "id": 64311411,
          "rate": 20
        }
      ],
      "needLv": 10,
      "battleMapLowLv": [
        {
          "id": 64311402,
          "rate": 40
        },
        {
          "id": 64311404,
          "rate": 40
        },
        {
          "id": 64311410,
          "rate": 40
        },
        {
          "id": 64311411,
          "rate": 40
        }
      ]
    },
    "64500045": {
      "id": 64500045,
      "name": "좌우반전_다도_사막 지형",
      "battleMap": [
        {
          "id": 64311405,
          "rate": 20
        },
        {
          "id": 64311406,
          "rate": 20
        },
        {
          "id": 64311413,
          "rate": 20
        },
        {
          "id": 64311414,
          "rate": 20
        }
      ],
      "needLv": 10,
      "battleMapLowLv": [
        {
          "id": 64311406,
          "rate": 40
        }
      ]
    },
    "64500046": {
      "id": 64500046,
      "name": "좌우반전_다도_눈 지형",
      "battleMap": [
        {
          "id": 64311408,
          "rate": 20
        },
        {
          "id": 64311417,
          "rate": 40
        },
        {
          "id": 64311418,
          "rate": 20
        }
      ],
      "needLv": 10,
      "battleMapLowLv": [
        {
          "id": 64311408,
          "rate": 40
        }
      ]
    },
    "64500047": {
      "id": 64500047,
      "name": "좌우반전_대형섬_초원 지형",
      "battleMap": [
        {
          "id": 64311501,
          "rate": 15
        },
        {
          "id": 64311502,
          "rate": 20
        },
        {
          "id": 64311504,
          "rate": 20
        },
        {
          "id": 64311509,
          "rate": 20
        },
        {
          "id": 64310510,
          "rate": 15
        }
      ],
      "needLv": 10,
      "battleMapLowLv": [
        {
          "id": 64311501,
          "rate": 40
        },
        {
          "id": 64311504,
          "rate": 40
        },
        {
          "id": 64311509,
          "rate": 40
        }
      ]
    },
    "64500048": {
      "id": 64500048,
      "name": "좌우반전_대형섬_사막 지형",
      "battleMap": [
        {
          "id": 64311505,
          "rate": 20
        },
        {
          "id": 64311506,
          "rate": 40
        }
      ],
      "needLv": 10,
      "battleMapLowLv": [
        {
          "id": 64311506,
          "rate": 40
        }
      ]
    },
    "64500049": {
      "id": 64500049,
      "name": "좌우반전_대형섬_눈 지형",
      "battleMap": [
        {
          "id": 64311507,
          "rate": 20
        },
        {
          "id": 64311508,
          "rate": 20
        }
      ],
      "needLv": 10,
      "battleMapLowLv": [
        {
          "id": 64311508,
          "rate": 40
        }
      ]
    },
    "64500050": {
      "id": 64500050,
      "name": "좌우반전_일반강_초원 지형",
      "battleMap": [
        {
          "id": 64311601,
          "rate": 20
        },
        {
          "id": 64311603,
          "rate": 15
        },
        {
          "id": 64311604,
          "rate": 10
        }
      ],
      "needLv": 10,
      "battleMapLowLv": [
        {
          "id": 64311601,
          "rate": 40
        }
      ]
    },
    "64500051": {
      "id": 64500051,
      "name": "좌우반전_일반강_사막 지형",
      "battleMap": [
        {
          "id": 64311605,
          "rate": 20
        },
        {
          "id": 64311606,
          "rate": 20
        }
      ],
      "needLv": 10,
      "battleMapLowLv": [
        {
          "id": 64311605,
          "rate": 40
        }
      ]
    },
    "64500052": {
      "id": 64500052,
      "name": "좌우반전_일반강_눈 지형",
      "battleMap": [
        {
          "id": 64311607,
          "rate": 20
        },
        {
          "id": 64311608,
          "rate": 20
        }
      ],
      "needLv": 10,
      "battleMapLowLv": [
        {
          "id": 64311607,
          "rate": 40
        }
      ]
    },
    "64500053": {
      "id": 64500053,
      "name": "좌우반전_구불거리는강_초원 지형",
      "battleMap": [
        {
          "id": 64311701,
          "rate": 20
        },
        {
          "id": 64311702,
          "rate": 20
        },
        {
          "id": 64311703,
          "rate": 15
        },
        {
          "id": 64311704,
          "rate": 15
        }
      ],
      "needLv": 10,
      "battleMapLowLv": [
        {
          "id": 64311701,
          "rate": 40
        }
      ]
    },
    "64500054": {
      "id": 64500054,
      "name": "좌우반전_구불거리는강_사막 지형",
      "battleMap": [
        {
          "id": 64311705,
          "rate": 20
        },
        {
          "id": 64311706,
          "rate": 15
        }
      ],
      "needLv": 10,
      "battleMapLowLv": [
        {
          "id": 64311705,
          "rate": 40
        }
      ]
    },
    "64500055": {
      "id": 64500055,
      "name": "좌우반전_구불거리는강_눈 지형",
      "battleMap": [
        {
          "id": 64311707,
          "rate": 15
        },
        {
          "id": 64311708,
          "rate": 15
        }
      ],
      "needLv": 10,
      "battleMapLowLv": [
        {
          "id": 64311707,
          "rate": 40
        }
      ]
    },
    "64500056": {
      "id": 64500056,
      "name": "좌우반전_모이는강_초원 지형",
      "battleMap": [
        {
          "id": 64311801,
          "rate": 20
        },
        {
          "id": 64311802,
          "rate": 20
        },
        {
          "id": 64311803,
          "rate": 20
        },
        {
          "id": 64311804,
          "rate": 20
        }
      ],
      "needLv": 10,
      "battleMapLowLv": [
        {
          "id": 64311801,
          "rate": 40
        }
      ]
    },
    "64500057": {
      "id": 64500057,
      "name": "좌우반전_모이는강_사막 지형",
      "battleMap": [
        {
          "id": 64311805,
          "rate": 15
        },
        {
          "id": 64311806,
          "rate": 20
        }
      ],
      "needLv": 10,
      "battleMapLowLv": [
        {
          "id": 64311805,
          "rate": 40
        }
      ]
    },
    "64500058": {
      "id": 64500058,
      "name": "좌우반전_모이는강_눈 지형",
      "battleMap": [
        {
          "id": 64311807,
          "rate": 20
        },
        {
          "id": 64311808,
          "rate": 20
        }
      ],
      "needLv": 10,
      "battleMapLowLv": [
        {
          "id": 64311807,
          "rate": 40
        }
      ]
    },
    "64500059": {
      "id": 64500059,
      "name": "좌우반전_해협_초원 지형",
      "battleMap": [
        {
          "id": 64311901,
          "rate": 20
        },
        {
          "id": 64311903,
          "rate": 20
        },
        {
          "id": 64311904,
          "rate": 20
        }
      ],
      "needLv": 10,
      "battleMapLowLv": [
        {
          "id": 64311901,
          "rate": 40
        },
        {
          "id": 64311904,
          "rate": 40
        }
      ]
    },
    "64500060": {
      "id": 64500060,
      "name": "좌우반전_해협_사막 지형",
      "battleMap": [
        {
          "id": 64311905,
          "rate": 20
        },
        {
          "id": 64311906,
          "rate": 20
        }
      ],
      "needLv": 10,
      "battleMapLowLv": [
        {
          "id": 64311905,
          "rate": 40
        }
      ]
    },
    "64500061": {
      "id": 64500061,
      "name": "좌우반전_해협_눈 지형",
      "battleMap": [
        {
          "id": 64311907,
          "rate": 20
        },
        {
          "id": 64311908,
          "rate": 20
        }
      ],
      "needLv": 10,
      "battleMapLowLv": [
        {
          "id": 64311907,
          "rate": 40
        }
      ]
    }
  }
}
