{
  ":QuestGroup": {
    ":type": {
      "id": "key",
      "tagName": "text",
      "regenSec": "number"
    },
    ":required": {},
    ":min": {},
    ":max": {},
    ":enum": {},
    ":links": {}
  },
  "QuestGroup": {
    "99860000": {
      "id": 99860000,
      "tagName": "ë™ë§¹"
    },
    "99860001": {
      "id": 99860001
    },
    "99860002": {
      "id": 99860002
    },
    "99860003": {
      "id": 99860003
    },
    "99860004": {
      "id": 99860004
    },
    "99860005": {
      "id": 99860005
    },
    "99860006": {
      "id": 99860006
    },
    "99860007": {
      "id": 99860007
    },
    "99860008": {
      "id": 99860008
    },
    "99860201": {
      "id": 99860201
    },
    "99860202": {
      "id": 99860202
    },
    "99860203": {
      "id": 99860203
    },
    "99860204": {
      "id": 99860204
    },
    "99860205": {
      "id": 99860205
    },
    "99860206": {
      "id": 99860206
    },
    "99860207": {
      "id": 99860207
    },
    "99860208": {
      "id": 99860208
    },
    "99860209": {
      "id": 99860209
    },
    "99860210": {
      "id": 99860210
    },
    "99860211": {
      "id": 99860211
    },
    "99860212": {
      "id": 99860212
    },
    "99860213": {
      "id": 99860213
    },
    "99860214": {
      "id": 99860214
    },
    "99860215": {
      "id": 99860215
    },
    "99860216": {
      "id": 99860216
    },
    "99860217": {
      "id": 99860217
    },
    "99860218": {
      "id": 99860218
    },
    "99860219": {
      "id": 99860219
    },
    "99860220": {
      "id": 99860220
    },
    "99860221": {
      "id": 99860221
    },
    "99860222": {
      "id": 99860222
    },
    "99860223": {
      "id": 99860223
    },
    "99860224": {
      "id": 99860224
    },
    "99860225": {
      "id": 99860225
    },
    "99860226": {
      "id": 99860226
    },
    "99860227": {
      "id": 99860227
    },
    "99860228": {
      "id": 99860228
    },
    "99860229": {
      "id": 99860229
    },
    "99860230": {
      "id": 99860230
    },
    "99860231": {
      "id": 99860231
    },
    "99860232": {
      "id": 99860232
    },
    "99860233": {
      "id": 99860233
    },
    "99860301": {
      "id": 99860301
    },
    "99860302": {
      "id": 99860302
    },
    "99860303": {
      "id": 99860303
    },
    "99860304": {
      "id": 99860304
    },
    "99860305": {
      "id": 99860305
    },
    "99860306": {
      "id": 99860306
    },
    "99860307": {
      "id": 99860307
    },
    "99860308": {
      "id": 99860308
    },
    "99860401": {
      "id": 99860401
    },
    "99860402": {
      "id": 99860402
    },
    "99860403": {
      "id": 99860403
    },
    "99860404": {
      "id": 99860404
    },
    "99860405": {
      "id": 99860405
    },
    "99860406": {
      "id": 99860406
    },
    "99860407": {
      "id": 99860407
    },
    "99860408": {
      "id": 99860408
    },
    "99860501": {
      "id": 99860501
    },
    "99860502": {
      "id": 99860502
    },
    "99860503": {
      "id": 99860503
    },
    "99860504": {
      "id": 99860504
    },
    "99860505": {
      "id": 99860505
    },
    "99860506": {
      "id": 99860506
    },
    "99860507": {
      "id": 99860507
    },
    "99860508": {
      "id": 99860508
    },
    "99860998": {
      "id": 99860998,
      "regenSec": 600
    },
    "99860999": {
      "id": 99860999,
      "regenSec": 3600
    }
  }
}